cbsave/__main__.py
cbsave-0.3.0.dist-info/WHEEL
cbsave-0.3.0.dist-info/METADATA
cbsave-0.3.0.dist-info/RECORD
